[
    {
        "QsdaVersion":  "2.1.0",
        "ObjectId":  "vNrppF",
        "CalcTime":  "0",
        "NumOfColumns":  "0",
        "MeasureCount":  "-1",
        "DimensionCount":  "-1",
        "NumOfRows":  "0",
        "BookmarkApplied":  "",
        "ErrorCode":  "0",
        "CalcConditionUnfulfilled":  "False"
    },
    {
        "QsdaVersion":  "2.1.0",
        "ObjectId":  "ejfUkm",
        "CalcTime":  "0.062",
        "NumOfColumns":  "1",
        "MeasureCount":  "-1",
        "DimensionCount":  "-1",
        "NumOfRows":  "6",
        "BookmarkApplied":  "",
        "ErrorCode":  "0",
        "CalcConditionUnfulfilled":  "False"
    },
    {
        "QsdaVersion":  "2.1.0",
        "ObjectId":  "mkPzS",
        "CalcTime":  "0.032",
        "NumOfColumns":  "0",
        "MeasureCount":  "-1",
        "DimensionCount":  "-1",
        "NumOfRows":  "0",
        "BookmarkApplied":  "",
        "ErrorCode":  "0",
        "CalcConditionUnfulfilled":  "False"
    },
    {
        "QsdaVersion":  "2.1.0",
        "ObjectId":  "KsMbZjN",
        "CalcTime":  "0.032",
        "NumOfColumns":  "1",
        "MeasureCount":  "-1",
        "DimensionCount":  "-1",
        "NumOfRows":  "2",
        "BookmarkApplied":  "",
        "ErrorCode":  "0",
        "CalcConditionUnfulfilled":  "False"
    },
    {
        "QsdaVersion":  "2.1.0",
        "ObjectId":  "VmuUwpD",
        "CalcTime":  "0.031",
        "NumOfColumns":  "1",
        "MeasureCount":  "-1",
        "DimensionCount":  "-1",
        "NumOfRows":  "3",
        "BookmarkApplied":  "",
        "ErrorCode":  "0",
        "CalcConditionUnfulfilled":  "False"
    },
    {
        "QsdaVersion":  "2.1.0",
        "ObjectId":  "kzzxmjj",
        "CalcTime":  "0.048",
        "NumOfColumns":  "1",
        "MeasureCount":  "-1",
        "DimensionCount":  "-1",
        "NumOfRows":  "5",
        "BookmarkApplied":  "",
        "ErrorCode":  "0",
        "CalcConditionUnfulfilled":  "False"
    },
    {
        "QsdaVersion":  "2.1.0",
        "ObjectId":  "brppex",
        "CalcTime":  "0.03",
        "NumOfColumns":  "0",
        "MeasureCount":  "-1",
        "DimensionCount":  "-1",
        "NumOfRows":  "0",
        "BookmarkApplied":  "",
        "ErrorCode":  "0",
        "CalcConditionUnfulfilled":  "False"
    },
    {
        "QsdaVersion":  "2.1.0",
        "ObjectId":  "wzJGP",
        "CalcTime":  "0.053",
        "NumOfColumns":  "0",
        "MeasureCount":  "-1",
        "DimensionCount":  "-1",
        "NumOfRows":  "0",
        "BookmarkApplied":  "",
        "ErrorCode":  "0",
        "CalcConditionUnfulfilled":  "False"
    },
    {
        "QsdaVersion":  "2.1.0",
        "ObjectId":  "kTtWWj",
        "CalcTime":  "0.031",
        "NumOfColumns":  "0",
        "MeasureCount":  "-1",
        "DimensionCount":  "-1",
        "NumOfRows":  "0",
        "BookmarkApplied":  "",
        "ErrorCode":  "0",
        "CalcConditionUnfulfilled":  "False"
    },
    {
        "QsdaVersion":  "2.1.0",
        "ObjectId":  "jLNaMJ",
        "CalcTime":  "0.035",
        "NumOfColumns":  "1",
        "MeasureCount":  "1",
        "DimensionCount":  "1",
        "NumOfRows":  "1",
        "BookmarkApplied":  "",
        "ErrorCode":  "0",
        "CalcConditionUnfulfilled":  "False"
    },
    {
        "QsdaVersion":  "2.1.0",
        "ObjectId":  "mLPvhj",
        "CalcTime":  "0.034",
        "NumOfColumns":  "1",
        "MeasureCount":  "1",
        "DimensionCount":  "1",
        "NumOfRows":  "4",
        "BookmarkApplied":  "",
        "ErrorCode":  "0",
        "CalcConditionUnfulfilled":  "False"
    },
    {
        "QsdaVersion":  "2.1.0",
        "ObjectId":  "wJQmub",
        "CalcTime":  "0.041",
        "NumOfColumns":  "3",
        "MeasureCount":  "3",
        "DimensionCount":  "1",
        "NumOfRows":  "6",
        "BookmarkApplied":  "",
        "ErrorCode":  "0",
        "CalcConditionUnfulfilled":  "False"
    },
    {
        "QsdaVersion":  "2.1.0",
        "ObjectId":  "Lhjt",
        "CalcTime":  "0.044",
        "NumOfColumns":  "6",
        "MeasureCount":  "6",
        "DimensionCount":  "1",
        "NumOfRows":  "1",
        "BookmarkApplied":  "",
        "ErrorCode":  "0",
        "CalcConditionUnfulfilled":  "False"
    },
    {
        "QsdaVersion":  "2.1.0",
        "ObjectId":  "wDeNay",
        "CalcTime":  "0.038",
        "NumOfColumns":  "0",
        "MeasureCount":  "-1",
        "DimensionCount":  "-1",
        "NumOfRows":  "0",
        "BookmarkApplied":  "",
        "ErrorCode":  "0",
        "CalcConditionUnfulfilled":  "False"
    },
    {
        "QsdaVersion":  "2.1.0",
        "ObjectId":  "hPpHWQ",
        "CalcTime":  "0",
        "NumOfColumns":  "0",
        "MeasureCount":  "-1",
        "DimensionCount":  "-1",
        "NumOfRows":  "0",
        "BookmarkApplied":  "",
        "ErrorCode":  "0",
        "CalcConditionUnfulfilled":  "False"
    },
    {
        "QsdaVersion":  "2.1.0",
        "ObjectId":  "GYLsCMn",
        "CalcTime":  "0.035",
        "NumOfColumns":  "1",
        "MeasureCount":  "-1",
        "DimensionCount":  "-1",
        "NumOfRows":  "6",
        "BookmarkApplied":  "",
        "ErrorCode":  "0",
        "CalcConditionUnfulfilled":  "False"
    },
    {
        "QsdaVersion":  "2.1.0",
        "ObjectId":  "jGrLcP",
        "CalcTime":  "0.031",
        "NumOfColumns":  "0",
        "MeasureCount":  "-1",
        "DimensionCount":  "-1",
        "NumOfRows":  "0",
        "BookmarkApplied":  "",
        "ErrorCode":  "0",
        "CalcConditionUnfulfilled":  "False"
    },
    {
        "QsdaVersion":  "2.1.0",
        "ObjectId":  "jQstAP",
        "CalcTime":  "0.291",
        "NumOfColumns":  "1",
        "MeasureCount":  "-1",
        "DimensionCount":  "-1",
        "NumOfRows":  "2",
        "BookmarkApplied":  "",
        "ErrorCode":  "0",
        "CalcConditionUnfulfilled":  "False"
    },
    {
        "QsdaVersion":  "2.1.0",
        "ObjectId":  "jzHzMk",
        "CalcTime":  "0.032",
        "NumOfColumns":  "1",
        "MeasureCount":  "-1",
        "DimensionCount":  "-1",
        "NumOfRows":  "3",
        "BookmarkApplied":  "",
        "ErrorCode":  "0",
        "CalcConditionUnfulfilled":  "False"
    },
    {
        "QsdaVersion":  "2.1.0",
        "ObjectId":  "fct",
        "CalcTime":  "0.03",
        "NumOfColumns":  "1",
        "MeasureCount":  "-1",
        "DimensionCount":  "-1",
        "NumOfRows":  "5",
        "BookmarkApplied":  "",
        "ErrorCode":  "0",
        "CalcConditionUnfulfilled":  "False"
    },
    {
        "QsdaVersion":  "2.1.0",
        "ObjectId":  "Lmmdg",
        "CalcTime":  "0.031",
        "NumOfColumns":  "0",
        "MeasureCount":  "-1",
        "DimensionCount":  "-1",
        "NumOfRows":  "0",
        "BookmarkApplied":  "",
        "ErrorCode":  "0",
        "CalcConditionUnfulfilled":  "False"
    },
    {
        "QsdaVersion":  "2.1.0",
        "ObjectId":  "sjzCJtS",
        "CalcTime":  "0.033",
        "NumOfColumns":  "0",
        "MeasureCount":  "-1",
        "DimensionCount":  "-1",
        "NumOfRows":  "0",
        "BookmarkApplied":  "",
        "ErrorCode":  "0",
        "CalcConditionUnfulfilled":  "False"
    },
    {
        "QsdaVersion":  "2.1.0",
        "ObjectId":  "fwwNdp",
        "CalcTime":  "0.035",
        "NumOfColumns":  "0",
        "MeasureCount":  "-1",
        "DimensionCount":  "-1",
        "NumOfRows":  "0",
        "BookmarkApplied":  "",
        "ErrorCode":  "0",
        "CalcConditionUnfulfilled":  "False"
    },
    {
        "QsdaVersion":  "2.1.0",
        "ObjectId":  "amkVD",
        "CalcTime":  "0.037",
        "NumOfColumns":  "1",
        "MeasureCount":  "2",
        "DimensionCount":  "0",
        "NumOfRows":  "1",
        "BookmarkApplied":  "",
        "ErrorCode":  "0",
        "CalcConditionUnfulfilled":  "False"
    },
    {
        "QsdaVersion":  "2.1.0",
        "ObjectId":  "ukjpxP",
        "CalcTime":  "0.033",
        "NumOfColumns":  "1",
        "MeasureCount":  "2",
        "DimensionCount":  "0",
        "NumOfRows":  "1",
        "BookmarkApplied":  "",
        "ErrorCode":  "0",
        "CalcConditionUnfulfilled":  "False"
    },
    {
        "QsdaVersion":  "2.1.0",
        "ObjectId":  "YgvbH",
        "CalcTime":  "0.036",
        "NumOfColumns":  "1",
        "MeasureCount":  "1",
        "DimensionCount":  "1",
        "NumOfRows":  "2",
        "BookmarkApplied":  "",
        "ErrorCode":  "0",
        "CalcConditionUnfulfilled":  "False"
    },
    {
        "QsdaVersion":  "2.1.0",
        "ObjectId":  "kAdR",
        "CalcTime":  "0.039",
        "NumOfColumns":  "10",
        "MeasureCount":  "0",
        "DimensionCount":  "11",
        "NumOfRows":  "1065",
        "BookmarkApplied":  "",
        "ErrorCode":  "0",
        "CalcConditionUnfulfilled":  "False"
    },
    {
        "QsdaVersion":  "2.1.0",
        "ObjectId":  "ZBpm",
        "CalcTime":  "0.033",
        "NumOfColumns":  "1",
        "MeasureCount":  "2",
        "DimensionCount":  "0",
        "NumOfRows":  "1",
        "BookmarkApplied":  "",
        "ErrorCode":  "0",
        "CalcConditionUnfulfilled":  "False"
    },
    {
        "QsdaVersion":  "2.1.0",
        "ObjectId":  "mXs",
        "CalcTime":  "0.035",
        "NumOfColumns":  "1",
        "MeasureCount":  "2",
        "DimensionCount":  "0",
        "NumOfRows":  "1",
        "BookmarkApplied":  "",
        "ErrorCode":  "0",
        "CalcConditionUnfulfilled":  "False"
    },
    {
        "QsdaVersion":  "2.1.0",
        "ObjectId":  "bJBvMDz",
        "CalcTime":  "0.044",
        "NumOfColumns":  "1",
        "MeasureCount":  "2",
        "DimensionCount":  "0",
        "NumOfRows":  "1",
        "BookmarkApplied":  "",
        "ErrorCode":  "0",
        "CalcConditionUnfulfilled":  "False"
    },
    {
        "QsdaVersion":  "2.1.0",
        "ObjectId":  "hJazvNF",
        "CalcTime":  "0.032",
        "NumOfColumns":  "0",
        "MeasureCount":  "-1",
        "DimensionCount":  "-1",
        "NumOfRows":  "0",
        "BookmarkApplied":  "",
        "ErrorCode":  "0",
        "CalcConditionUnfulfilled":  "False"
    },
    {
        "QsdaVersion":  "2.1.0",
        "ObjectId":  "tfSJqP",
        "CalcTime":  "0.035",
        "NumOfColumns":  "0",
        "MeasureCount":  "-1",
        "DimensionCount":  "-1",
        "NumOfRows":  "0",
        "BookmarkApplied":  "",
        "ErrorCode":  "0",
        "CalcConditionUnfulfilled":  "False"
    },
    {
        "QsdaVersion":  "2.1.0",
        "ObjectId":  "Fvnwt",
        "CalcTime":  "0.039",
        "NumOfColumns":  "0",
        "MeasureCount":  "-1",
        "DimensionCount":  "-1",
        "NumOfRows":  "0",
        "BookmarkApplied":  "",
        "ErrorCode":  "0",
        "CalcConditionUnfulfilled":  "False"
    },
    {
        "QsdaVersion":  "2.1.0",
        "ObjectId":  "NRfvgx",
        "CalcTime":  "0.032",
        "NumOfColumns":  "0",
        "MeasureCount":  "1",
        "DimensionCount":  "0",
        "NumOfRows":  "1",
        "BookmarkApplied":  "",
        "ErrorCode":  "0",
        "CalcConditionUnfulfilled":  "False"
    },
    {
        "QsdaVersion":  "2.1.0",
        "ObjectId":  "b254753b-ccf9-4ab7-813f-a1fe238b6513",
        "CalcTime":  "0.04",
        "NumOfColumns":  "0",
        "MeasureCount":  "-1",
        "DimensionCount":  "-1",
        "NumOfRows":  "0",
        "BookmarkApplied":  "",
        "ErrorCode":  "0",
        "CalcConditionUnfulfilled":  "False"
    },
    {
        "QsdaVersion":  "2.1.0",
        "ObjectId":  "WLSaXmh",
        "CalcTime":  "0.048",
        "NumOfColumns":  "7",
        "MeasureCount":  "0",
        "DimensionCount":  "11",
        "NumOfRows":  "12",
        "BookmarkApplied":  "",
        "ErrorCode":  "0",
        "CalcConditionUnfulfilled":  "False"
    },
    {
        "QsdaVersion":  "2.1.0",
        "ObjectId":  "a0d3228a-3ac4-409c-8ae3-40374e1f31f9",
        "CalcTime":  "0.037",
        "NumOfColumns":  "0",
        "MeasureCount":  "-1",
        "DimensionCount":  "-1",
        "NumOfRows":  "0",
        "BookmarkApplied":  "",
        "ErrorCode":  "0",
        "CalcConditionUnfulfilled":  "False"
    },
    {
        "QsdaVersion":  "2.1.0",
        "ObjectId":  "45ebfb4e-88df-44c9-aecc-f09edc8d9f13",
        "CalcTime":  "0.034",
        "NumOfColumns":  "0",
        "MeasureCount":  "-1",
        "DimensionCount":  "-1",
        "NumOfRows":  "0",
        "BookmarkApplied":  "",
        "ErrorCode":  "0",
        "CalcConditionUnfulfilled":  "False"
    },
    {
        "QsdaVersion":  "2.1.0",
        "ObjectId":  "yMSnKJU",
        "CalcTime":  "0.043",
        "NumOfColumns":  "5",
        "MeasureCount":  "1",
        "DimensionCount":  "6",
        "NumOfRows":  "1",
        "BookmarkApplied":  "",
        "ErrorCode":  "0",
        "CalcConditionUnfulfilled":  "False"
    },
    {
        "QsdaVersion":  "2.1.0",
        "ObjectId":  "7901fdea-27ef-4541-92df-55466c2942a6",
        "CalcTime":  "0.036",
        "NumOfColumns":  "0",
        "MeasureCount":  "-1",
        "DimensionCount":  "-1",
        "NumOfRows":  "0",
        "BookmarkApplied":  "",
        "ErrorCode":  "0",
        "CalcConditionUnfulfilled":  "False"
    },
    {
        "QsdaVersion":  "2.1.0",
        "ObjectId":  "8fb9849d-39cb-44e4-8884-a342158e88b4",
        "CalcTime":  "0.055",
        "NumOfColumns":  "0",
        "MeasureCount":  "-1",
        "DimensionCount":  "-1",
        "NumOfRows":  "0",
        "BookmarkApplied":  "",
        "ErrorCode":  "0",
        "CalcConditionUnfulfilled":  "False"
    },
    {
        "QsdaVersion":  "2.1.0",
        "ObjectId":  "CzPBuxZ",
        "CalcTime":  "0.042",
        "NumOfColumns":  "3",
        "MeasureCount":  "0",
        "DimensionCount":  "4",
        "NumOfRows":  "1069",
        "BookmarkApplied":  "",
        "ErrorCode":  "0",
        "CalcConditionUnfulfilled":  "False"
    },
    {
        "QsdaVersion":  "2.1.0",
        "ObjectId":  "QPKSaT",
        "CalcTime":  "0.032",
        "NumOfColumns":  "0",
        "MeasureCount":  "1",
        "DimensionCount":  "0",
        "NumOfRows":  "1",
        "BookmarkApplied":  "",
        "ErrorCode":  "0",
        "CalcConditionUnfulfilled":  "False"
    },
    {
        "QsdaVersion":  "2.1.0",
        "ObjectId":  "dVLmpv",
        "CalcTime":  "0.036",
        "NumOfColumns":  "0",
        "MeasureCount":  "1",
        "DimensionCount":  "0",
        "NumOfRows":  "1",
        "BookmarkApplied":  "",
        "ErrorCode":  "0",
        "CalcConditionUnfulfilled":  "False"
    },
    {
        "QsdaVersion":  "2.1.0",
        "ObjectId":  "da0b14c3-5808-419a-a425-bc07ef8cbab0",
        "CalcTime":  "0.131",
        "NumOfColumns":  "0",
        "MeasureCount":  "-1",
        "DimensionCount":  "-1",
        "NumOfRows":  "0",
        "BookmarkApplied":  "",
        "ErrorCode":  "0",
        "CalcConditionUnfulfilled":  "False"
    },
    {
        "QsdaVersion":  "2.1.0",
        "ObjectId":  "euSZ",
        "CalcTime":  "0.032",
        "NumOfColumns":  "0",
        "MeasureCount":  "1",
        "DimensionCount":  "0",
        "NumOfRows":  "1",
        "BookmarkApplied":  "",
        "ErrorCode":  "0",
        "CalcConditionUnfulfilled":  "False"
    },
    {
        "QsdaVersion":  "2.1.0",
        "ObjectId":  "hmHpp",
        "CalcTime":  "0.033",
        "NumOfColumns":  "0",
        "MeasureCount":  "-1",
        "DimensionCount":  "-1",
        "NumOfRows":  "0",
        "BookmarkApplied":  "",
        "ErrorCode":  "0",
        "CalcConditionUnfulfilled":  "False"
    },
    {
        "QsdaVersion":  "2.1.0",
        "ObjectId":  "rtvXQc",
        "CalcTime":  "0.036",
        "NumOfColumns":  "0",
        "MeasureCount":  "-1",
        "DimensionCount":  "-1",
        "NumOfRows":  "0",
        "BookmarkApplied":  "",
        "ErrorCode":  "0",
        "CalcConditionUnfulfilled":  "False"
    }
]
