[
    {
        "QsdaVersion":  "2.1.0",
        "Flag":  "UnusedField",
        "Category":  "Resource",
        "Label":  "Unused Field",
        "Description":  "The field \"CommunityID\" was not used in any charts or master items. This field could likely be dropped from the data model with no loss of analysis. Dropping this field would recover 57 bytes.",
        "Impact":  "57",
        "RefObjectType":  "FieldMeta",
        "RefMetaId":  "6"
    },
    {
        "QsdaVersion":  "2.1.0",
        "Flag":  "UnusedField",
        "Category":  "Resource",
        "Label":  "Unused Field",
        "Description":  "The field \"SVP\" was not used in any charts or master items. This field could likely be dropped from the data model with no loss of analysis. Dropping this field would recover 21 bytes.",
        "Impact":  "21",
        "RefObjectType":  "FieldMeta",
        "RefMetaId":  "9"
    },
    {
        "QsdaVersion":  "2.1.0",
        "Flag":  "UnusedField",
        "Category":  "Resource",
        "Label":  "Unused Field",
        "Description":  "The field \"RVP\" was not used in any charts or master items. This field could likely be dropped from the data model with no loss of analysis. Dropping this field would recover 80 bytes.",
        "Impact":  "80",
        "RefObjectType":  "FieldMeta",
        "RefMetaId":  "11"
    },
    {
        "QsdaVersion":  "2.1.0",
        "Flag":  "UnusedField",
        "Category":  "Resource",
        "Label":  "Unused Field",
        "Description":  "The field \"CommunityState\" was not used in any charts or master items. This field could likely be dropped from the data model with no loss of analysis. Dropping this field would recover 48 bytes.",
        "Impact":  "48",
        "RefObjectType":  "FieldMeta",
        "RefMetaId":  "12"
    },
    {
        "QsdaVersion":  "2.1.0",
        "Flag":  "UnusedField",
        "Category":  "Resource",
        "Label":  "Unused Field",
        "Description":  "The field \"CommunityCountry\" was not used in any charts or master items. This field could likely be dropped from the data model with no loss of analysis. Dropping this field would recover 11 bytes.",
        "Impact":  "11",
        "RefObjectType":  "FieldMeta",
        "RefMetaId":  "13"
    },
    {
        "QsdaVersion":  "2.1.0",
        "Flag":  "UnusedField",
        "Category":  "Resource",
        "Label":  "Unused Field",
        "Description":  "The field \"OutcomeFlg\" was not used in any charts or master items. This field could likely be dropped from the data model with no loss of analysis. Dropping this field would recover 14 bytes.",
        "Impact":  "14",
        "RefObjectType":  "FieldMeta",
        "RefMetaId":  "20"
    },
    {
        "QsdaVersion":  "2.1.0",
        "Flag":  "UnusedField",
        "Category":  "Resource",
        "Label":  "Unused Field",
        "Description":  "The field \"FactType\" was not used in any charts or master items. This field could likely be dropped from the data model with no loss of analysis. Dropping this field would recover 17 bytes.",
        "Impact":  "17",
        "RefObjectType":  "FieldMeta",
        "RefMetaId":  "22"
    },
    {
        "QsdaVersion":  "2.1.0",
        "Flag":  "UnusedField",
        "Category":  "Resource",
        "Label":  "Unused Field",
        "Description":  "The field \"IncidentTM\" was not used in any charts or master items. This field could likely be dropped from the data model with no loss of analysis. Dropping this field would recover 51 bytes.",
        "Impact":  "51",
        "RefObjectType":  "FieldMeta",
        "RefMetaId":  "23"
    },
    {
        "QsdaVersion":  "2.1.0",
        "Flag":  "UnusedField",
        "Category":  "Resource",
        "Label":  "Unused Field",
        "Description":  "The field \"IncidentPriority\" was not used in any charts or master items. This field could likely be dropped from the data model with no loss of analysis. Dropping this field would recover 0 bytes.",
        "Impact":  "0",
        "RefObjectType":  "FieldMeta",
        "RefMetaId":  "28"
    },
    {
        "QsdaVersion":  "2.1.0",
        "Flag":  "UnusedField",
        "Category":  "Resource",
        "Label":  "Unused Field",
        "Description":  "The field \"TimePeriod\" was not used in any charts or master items. This field could likely be dropped from the data model with no loss of analysis. Dropping this field would recover 16 bytes.",
        "Impact":  "16",
        "RefObjectType":  "FieldMeta",
        "RefMetaId":  "33"
    },
    {
        "QsdaVersion":  "2.1.0",
        "Flag":  "UnusedField",
        "Category":  "Resource",
        "Label":  "Unused Field",
        "Description":  "The field \"IncidentFlg\" was not used in any charts or master items. This field could likely be dropped from the data model with no loss of analysis. Dropping this field would recover 14 bytes.",
        "Impact":  "14",
        "RefObjectType":  "FieldMeta",
        "RefMetaId":  "35"
    },
    {
        "QsdaVersion":  "2.1.0",
        "Flag":  "UnusedField",
        "Category":  "Resource",
        "Label":  "Unused Field",
        "Description":  "The field \"CMSResidentDashboard\" was not used in any charts or master items. This field could likely be dropped from the data model with no loss of analysis. Dropping this field would recover 979 bytes.",
        "Impact":  "979",
        "RefObjectType":  "FieldMeta",
        "RefMetaId":  "38"
    },
    {
        "QsdaVersion":  "2.1.0",
        "Flag":  "UnusedField",
        "Category":  "Resource",
        "Label":  "Unused Field",
        "Description":  "The field \"RMSLeaseManagement\" was not used in any charts or master items. This field could likely be dropped from the data model with no loss of analysis. Dropping this field would recover 804 bytes.",
        "Impact":  "804",
        "RefObjectType":  "FieldMeta",
        "RefMetaId":  "39"
    },
    {
        "QsdaVersion":  "2.1.0",
        "Flag":  "UnusedField",
        "Category":  "Resource",
        "Label":  "Unused Field",
        "Description":  "The field \"RoomNumber\" was not used in any charts or master items. This field could likely be dropped from the data model with no loss of analysis. Dropping this field would recover 0 bytes.",
        "Impact":  "0",
        "RefObjectType":  "FieldMeta",
        "RefMetaId":  "41"
    },
    {
        "QsdaVersion":  "2.1.0",
        "Flag":  "UnusedField",
        "Category":  "Resource",
        "Label":  "Unused Field",
        "Description":  "The field \"PayorType\" was not used in any charts or master items. This field could likely be dropped from the data model with no loss of analysis. Dropping this field would recover 0 bytes.",
        "Impact":  "0",
        "RefObjectType":  "FieldMeta",
        "RefMetaId":  "42"
    },
    {
        "QsdaVersion":  "2.1.0",
        "Flag":  "UnusedField",
        "Category":  "Resource",
        "Label":  "Unused Field",
        "Description":  "The field \"CurrentRent\" was not used in any charts or master items. This field could likely be dropped from the data model with no loss of analysis. Dropping this field would recover 0 bytes.",
        "Impact":  "0",
        "RefObjectType":  "FieldMeta",
        "RefMetaId":  "43"
    },
    {
        "QsdaVersion":  "2.1.0",
        "Flag":  "UnusedField",
        "Category":  "Resource",
        "Label":  "Unused Field",
        "Description":  "The field \"RoomTypeStyleCode\" was not used in any charts or master items. This field could likely be dropped from the data model with no loss of analysis. Dropping this field would recover 0 bytes.",
        "Impact":  "0",
        "RefObjectType":  "FieldMeta",
        "RefMetaId":  "44"
    },
    {
        "QsdaVersion":  "2.1.0",
        "Flag":  "UnusedField",
        "Category":  "Resource",
        "Label":  "Unused Field",
        "Description":  "The field \"AssessedCareRate\" was not used in any charts or master items. This field could likely be dropped from the data model with no loss of analysis. Dropping this field would recover 42 bytes.",
        "Impact":  "42",
        "RefObjectType":  "FieldMeta",
        "RefMetaId":  "45"
    },
    {
        "QsdaVersion":  "2.1.0",
        "Flag":  "UnusedField",
        "Category":  "Resource",
        "Label":  "Unused Field",
        "Description":  "The field \"AssessedMedRate\" was not used in any charts or master items. This field could likely be dropped from the data model with no loss of analysis. Dropping this field would recover 42 bytes.",
        "Impact":  "42",
        "RefObjectType":  "FieldMeta",
        "RefMetaId":  "46"
    },
    {
        "QsdaVersion":  "2.1.0",
        "Flag":  "UnusedField",
        "Category":  "Resource",
        "Label":  "Unused Field",
        "Description":  "The field \"IsPhysicalPresentFlg\" was not used in any charts or master items. This field could likely be dropped from the data model with no loss of analysis. Dropping this field would recover 0 bytes.",
        "Impact":  "0",
        "RefObjectType":  "FieldMeta",
        "RefMetaId":  "47"
    },
    {
        "QsdaVersion":  "2.1.0",
        "Flag":  "UnusedField",
        "Category":  "Resource",
        "Label":  "Unused Field",
        "Description":  "The field \"AssessedMedLevel\" was not used in any charts or master items. This field could likely be dropped from the data model with no loss of analysis. Dropping this field would recover 69 bytes.",
        "Impact":  "69",
        "RefObjectType":  "FieldMeta",
        "RefMetaId":  "50"
    },
    {
        "QsdaVersion":  "2.1.0",
        "Flag":  "UnusedField",
        "Category":  "Resource",
        "Label":  "Unused Field",
        "Description":  "The field \"Status\" was not used in any charts or master items. This field could likely be dropped from the data model with no loss of analysis. Dropping this field would recover 17 bytes.",
        "Impact":  "17",
        "RefObjectType":  "FieldMeta",
        "RefMetaId":  "51"
    },
    {
        "QsdaVersion":  "2.1.0",
        "Flag":  "UnusedField",
        "Category":  "Resource",
        "Label":  "Unused Field",
        "Description":  "The field \"MoveInDT\" was not used in any charts or master items. This field could likely be dropped from the data model with no loss of analysis. Dropping this field would recover 60 bytes.",
        "Impact":  "60",
        "RefObjectType":  "FieldMeta",
        "RefMetaId":  "52"
    },
    {
        "QsdaVersion":  "2.1.0",
        "Flag":  "UnusedField",
        "Category":  "Resource",
        "Label":  "Unused Field",
        "Description":  "The field \"NewMoveInFlg\" was not used in any charts or master items. This field could likely be dropped from the data model with no loss of analysis. Dropping this field would recover 14 bytes.",
        "Impact":  "14",
        "RefObjectType":  "FieldMeta",
        "RefMetaId":  "53"
    },
    {
        "QsdaVersion":  "2.1.0",
        "Flag":  "UnusedField",
        "Category":  "Resource",
        "Label":  "Unused Field",
        "Description":  "The field \"ScheduledMoveOutDT\" was not used in any charts or master items. This field could likely be dropped from the data model with no loss of analysis. Dropping this field would recover 3 bytes.",
        "Impact":  "3",
        "RefObjectType":  "FieldMeta",
        "RefMetaId":  "55"
    },
    {
        "QsdaVersion":  "2.1.0",
        "Flag":  "UnusedField",
        "Category":  "Resource",
        "Label":  "Unused Field",
        "Description":  "The field \"Gender\" was not used in any charts or master items. This field could likely be dropped from the data model with no loss of analysis. Dropping this field would recover 20 bytes.",
        "Impact":  "20",
        "RefObjectType":  "FieldMeta",
        "RefMetaId":  "56"
    },
    {
        "QsdaVersion":  "2.1.0",
        "Flag":  "UnusedField",
        "Category":  "Resource",
        "Label":  "Unused Field",
        "Description":  "The field \"UpcomingBirthdayFlg\" was not used in any charts or master items. This field could likely be dropped from the data model with no loss of analysis. Dropping this field would recover 14 bytes.",
        "Impact":  "14",
        "RefObjectType":  "FieldMeta",
        "RefMetaId":  "57"
    },
    {
        "QsdaVersion":  "2.1.0",
        "Flag":  "UnusedField",
        "Category":  "Resource",
        "Label":  "Unused Field",
        "Description":  "The field \"Age\" was not used in any charts or master items. This field could likely be dropped from the data model with no loss of analysis. Dropping this field would recover 42 bytes.",
        "Impact":  "42",
        "RefObjectType":  "FieldMeta",
        "RefMetaId":  "58"
    },
    {
        "QsdaVersion":  "2.1.0",
        "Flag":  "UnusedField",
        "Category":  "Resource",
        "Label":  "Unused Field",
        "Description":  "The field \"DOB\" was not used in any charts or master items. This field could likely be dropped from the data model with no loss of analysis. Dropping this field would recover 42 bytes.",
        "Impact":  "42",
        "RefObjectType":  "FieldMeta",
        "RefMetaId":  "59"
    },
    {
        "QsdaVersion":  "2.1.0",
        "Flag":  "UnusedField",
        "Category":  "Resource",
        "Label":  "Unused Field",
        "Description":  "The field \"BilledCareType\" was not used in any charts or master items. This field could likely be dropped from the data model with no loss of analysis. Dropping this field would recover 22 bytes.",
        "Impact":  "22",
        "RefObjectType":  "FieldMeta",
        "RefMetaId":  "60"
    },
    {
        "QsdaVersion":  "2.1.0",
        "Flag":  "UnusedField",
        "Category":  "Resource",
        "Label":  "Unused Field",
        "Description":  "The field \"BilledCareLevel\" was not used in any charts or master items. This field could likely be dropped from the data model with no loss of analysis. Dropping this field would recover 68 bytes.",
        "Impact":  "68",
        "RefObjectType":  "FieldMeta",
        "RefMetaId":  "61"
    },
    {
        "QsdaVersion":  "2.1.0",
        "Flag":  "UnusedField",
        "Category":  "Resource",
        "Label":  "Unused Field",
        "Description":  "The field \"DayName\" was not used in any charts or master items. This field could likely be dropped from the data model with no loss of analysis. Dropping this field would recover 234 bytes.",
        "Impact":  "234",
        "RefObjectType":  "FieldMeta",
        "RefMetaId":  "65"
    },
    {
        "QsdaVersion":  "2.1.0",
        "Flag":  "UnusedField",
        "Category":  "Resource",
        "Label":  "Unused Field",
        "Description":  "The field \"CurrentWeekFlg\" was not used in any charts or master items. This field could likely be dropped from the data model with no loss of analysis. Dropping this field would recover 57 bytes.",
        "Impact":  "57",
        "RefObjectType":  "FieldMeta",
        "RefMetaId":  "66"
    },
    {
        "QsdaVersion":  "2.1.0",
        "Flag":  "NullField",
        "Category":  "Resource",
        "Label":  "100% Null field",
        "Description":  "The field \"IncidentPriority\" contains only null values. This field could likely be dropped from the data model with no loss of analysis.",
        "Impact":  "0",
        "RefObjectType":  "FieldMeta",
        "RefMetaId":  "28"
    },
    {
        "QsdaVersion":  "2.1.0",
        "Flag":  "NullField",
        "Category":  "Resource",
        "Label":  "100% Null field",
        "Description":  "The field \"RoomNumber\" contains only null values. This field could likely be dropped from the data model with no loss of analysis.",
        "Impact":  "0",
        "RefObjectType":  "FieldMeta",
        "RefMetaId":  "41"
    },
    {
        "QsdaVersion":  "2.1.0",
        "Flag":  "NullField",
        "Category":  "Resource",
        "Label":  "100% Null field",
        "Description":  "The field \"PayorType\" contains only null values. This field could likely be dropped from the data model with no loss of analysis.",
        "Impact":  "0",
        "RefObjectType":  "FieldMeta",
        "RefMetaId":  "42"
    },
    {
        "QsdaVersion":  "2.1.0",
        "Flag":  "NullField",
        "Category":  "Resource",
        "Label":  "100% Null field",
        "Description":  "The field \"CurrentRent\" contains only null values. This field could likely be dropped from the data model with no loss of analysis.",
        "Impact":  "0",
        "RefObjectType":  "FieldMeta",
        "RefMetaId":  "43"
    },
    {
        "QsdaVersion":  "2.1.0",
        "Flag":  "NullField",
        "Category":  "Resource",
        "Label":  "100% Null field",
        "Description":  "The field \"RoomTypeStyleCode\" contains only null values. This field could likely be dropped from the data model with no loss of analysis.",
        "Impact":  "0",
        "RefObjectType":  "FieldMeta",
        "RefMetaId":  "44"
    },
    {
        "QsdaVersion":  "2.1.0",
        "Flag":  "NullField",
        "Category":  "Resource",
        "Label":  "100% Null field",
        "Description":  "The field \"IsPhysicalPresentFlg\" contains only null values. This field could likely be dropped from the data model with no loss of analysis.",
        "Impact":  "0",
        "RefObjectType":  "FieldMeta",
        "RefMetaId":  "47"
    },
    {
        "QsdaVersion":  "2.1.0",
        "Flag":  "AutoNumberKey",
        "Category":  "Resource",
        "Label":  "Key can be Autonumbered",
        "Description":  "This key field \"%CommunityKey\" was not found in any charts. Consider autonumbering to save 90 bytes of RAM.",
        "Impact":  "90",
        "RefObjectType":  "FieldMeta",
        "RefMetaId":  "5"
    },
    {
        "QsdaVersion":  "2.1.0",
        "Flag":  "DimensionSyntaxError",
        "Category":  "Quality",
        "Label":  "Dimension Syntax Error",
        "Description":  "The dimension failed validation. The error is:\\n Bad field name(s) \"ADLType\" .",
        "Impact":  "0",
        "RefObjectType":  "MasterDimensionMeta",
        "RefMetaId":  "85"
    },
    {
        "QsdaVersion":  "2.1.0",
        "Flag":  "MasterMeasDuplicateDef",
        "Category":  "Practice",
        "Label":  "Master Measure Duplicate Definition",
        "Description":  "Two or more Master Measures contain the same effective definition but use different names.  This may create ambiguity for Developers or Users. The Measures are: \"Avg Resident New, Avg # Incidents per Resident\"",
        "Impact":  "0",
        "RefObjectType":  "MasterMeasureMeta",
        "RefMetaId":  "92"
    },
    {
        "QsdaVersion":  "2.1.0",
        "Flag":  "ExpressionSyntaxError",
        "Category":  "Quality",
        "Label":  "Expression Syntax Error",
        "Description":  "The expression failed validation. The error is:\\n Bad field name(s) \"[# of Tasks Completed]\" \"[# of Tasks]\" .",
        "Impact":  "0",
        "RefObjectType":  "VizObjectExpressionMeta",
        "RefMetaId":  "357"
    },
    {
        "QsdaVersion":  "2.1.0",
        "Flag":  "ExpressionSyntaxError",
        "Category":  "Quality",
        "Label":  "Expression Syntax Error",
        "Description":  "The expression failed validation. The error is:\\n Bad field name(s) \"[# of Tasks Completed]\" \"[# of Tasks]\" .",
        "Impact":  "0",
        "RefObjectType":  "VizObjectExpressionMeta",
        "RefMetaId":  "358"
    },
    {
        "QsdaVersion":  "2.1.0",
        "Flag":  "ExpressionSyntaxError",
        "Category":  "Quality",
        "Label":  "Expression Syntax Error",
        "Description":  "The expression failed validation. The error is:\\n Bad field name(s) \"[# of Tasks Complete by Mobile]\" \"[# of Tasks]\" .",
        "Impact":  "0",
        "RefObjectType":  "VizObjectExpressionMeta",
        "RefMetaId":  "359"
    },
    {
        "QsdaVersion":  "2.1.0",
        "Flag":  "MultiTableExpression",
        "Category":  "Performance",
        "Label":  "Multi Table Expression",
        "Description":  "The  Expression  \"T30 Avg # of Incidents per Week\" contains an aggregation function that uses fields from 2 tables.  This requires Qlik calculation to perform an extra step of creating a temp table of field combinations. This extra step may have a negative impact on performance.",
        "Impact":  "0",
        "RefObjectType":  "VizObjectExpressionMeta",
        "RefMetaId":  "339"
    },
    {
        "QsdaVersion":  "2.1.0",
        "Flag":  "MultiTableExpression",
        "Category":  "Performance",
        "Label":  "Multi Table Expression",
        "Description":  "The  Expression  \"T60 Avg # of Incidents per Week\" contains an aggregation function that uses fields from 2 tables.  This requires Qlik calculation to perform an extra step of creating a temp table of field combinations. This extra step may have a negative impact on performance.",
        "Impact":  "0",
        "RefObjectType":  "MasterMeasureMeta",
        "RefMetaId":  "98"
    },
    {
        "QsdaVersion":  "2.1.0",
        "Flag":  "MultiTableExpression",
        "Category":  "Performance",
        "Label":  "Multi Table Expression",
        "Description":  "The  Expression  \"T30 Avg # of Incidents per Week\" contains an aggregation function that uses fields from 2 tables.  This requires Qlik calculation to perform an extra step of creating a temp table of field combinations. This extra step may have a negative impact on performance.",
        "Impact":  "0",
        "RefObjectType":  "MasterMeasureMeta",
        "RefMetaId":  "102"
    },
    {
        "QsdaVersion":  "2.1.0",
        "Flag":  "MissingMasterMeasure",
        "Category":  "Quality",
        "Label":  "Missing Master Measure",
        "Description":  "Measure in object \\\"Viz: x-kpi-double / Tasks Completed (Master Library) (Id:a6e50324-464c-4618-8fb5-2b1fb46a28ed)\\\" references non-existent Master Measure \"KDqKX\"",
        "Impact":  "0",
        "RefObjectType":  "VizObjectExpressionMeta",
        "RefMetaId":  "355"
    },
    {
        "QsdaVersion":  "2.1.0",
        "Flag":  "MissingMasterMeasure",
        "Category":  "Quality",
        "Label":  "Missing Master Measure",
        "Description":  "Measure in object \\\"Viz: x-kpi-double / Tasks Completed (Master Library) (Id:a6e50324-464c-4618-8fb5-2b1fb46a28ed)\\\" references non-existent Master Measure \"KvfpLUP\"",
        "Impact":  "0",
        "RefObjectType":  "VizObjectExpressionMeta",
        "RefMetaId":  "356"
    },
    {
        "QsdaVersion":  "2.1.0",
        "Flag":  "MissingExtension",
        "Category":  "Quality",
        "Label":  "Missing Extension",
        "Description":  "The Extension named \"x-kpi-double\"  is missing for visualization \"Viz: x-kpi-double / Tasks Completed (Master Library) (Id:a6e50324-464c-4618-8fb5-2b1fb46a28ed)\".",
        "Impact":  "0",
        "RefObjectType":  "VizObjectMeta",
        "RefMetaId":  "417"
    }
]
